{
  "table_name": "series",
  "row_count": 615,
  "columns": [
    {
      "name": "id",
      "type": "TEXT",
      "nullable": true,
      "default": null,
      "primary_key": true
    },
    {
      "name": "ticker",
      "type": "TEXT",
      "nullable": true,
      "default": null,
      "primary_key": false
    },
    {
      "name": "slug",
      "type": "TEXT",
      "nullable": true,
      "default": null,
      "primary_key": false
    },
    {
      "name": "title",
      "type": "TEXT",
      "nullable": true,
      "default": null,
      "primary_key": false
    },
    {
      "name": "subtitle",
      "type": "TEXT",
      "nullable": true,
      "default": null,
      "primary_key": false
    },
    {
      "name": "series_type",
      "type": "TEXT",
      "nullable": true,
      "default": null,
      "primary_key": false
    },
    {
      "name": "recurrence",
      "type": "TEXT",
      "nullable": true,
      "default": null,
      "primary_key": false
    },
    {
      "name": "description",
      "type": "TEXT",
      "nullable": true,
      "default": null,
      "primary_key": false
    },
    {
      "name": "image",
      "type": "TEXT",
      "nullable": true,
      "default": null,
      "primary_key": false
    },
    {
      "name": "icon",
      "type": "TEXT",
      "nullable": true,
      "default": null,
      "primary_key": false
    },
    {
      "name": "layout",
      "type": "TEXT",
      "nullable": true,
      "default": null,
      "primary_key": false
    },
    {
      "name": "active",
      "type": "INTEGER",
      "nullable": true,
      "default": "1",
      "primary_key": false
    },
    {
      "name": "closed",
      "type": "INTEGER",
      "nullable": true,
      "default": "0",
      "primary_key": false
    },
    {
      "name": "archived",
      "type": "INTEGER",
      "nullable": true,
      "default": "0",
      "primary_key": false
    },
    {
      "name": "new",
      "type": "INTEGER",
      "nullable": true,
      "default": "0",
      "primary_key": false
    },
    {
      "name": "featured",
      "type": "INTEGER",
      "nullable": true,
      "default": "0",
      "primary_key": false
    },
    {
      "name": "restricted",
      "type": "INTEGER",
      "nullable": true,
      "default": "0",
      "primary_key": false
    },
    {
      "name": "is_template",
      "type": "INTEGER",
      "nullable": true,
      "default": "0",
      "primary_key": false
    },
    {
      "name": "template_variables",
      "type": "INTEGER",
      "nullable": true,
      "default": "0",
      "primary_key": false
    },
    {
      "name": "published_at",
      "type": "TEXT",
      "nullable": true,
      "default": null,
      "primary_key": false
    },
    {
      "name": "created_by",
      "type": "TEXT",
      "nullable": true,
      "default": null,
      "primary_key": false
    },
    {
      "name": "updated_by",
      "type": "TEXT",
      "nullable": true,
      "default": null,
      "primary_key": false
    },
    {
      "name": "created_at",
      "type": "TEXT",
      "nullable": true,
      "default": null,
      "primary_key": false
    },
    {
      "name": "updated_at",
      "type": "TEXT",
      "nullable": true,
      "default": null,
      "primary_key": false
    },
    {
      "name": "comments_enabled",
      "type": "INTEGER",
      "nullable": true,
      "default": "0",
      "primary_key": false
    },
    {
      "name": "competitive",
      "type": "TEXT",
      "nullable": true,
      "default": null,
      "primary_key": false
    },
    {
      "name": "volume_24hr",
      "type": "REAL",
      "nullable": true,
      "default": "0",
      "primary_key": false
    },
    {
      "name": "volume",
      "type": "REAL",
      "nullable": true,
      "default": "0",
      "primary_key": false
    },
    {
      "name": "liquidity",
      "type": "REAL",
      "nullable": true,
      "default": "0",
      "primary_key": false
    },
    {
      "name": "start_date",
      "type": "TEXT",
      "nullable": true,
      "default": null,
      "primary_key": false
    },
    {
      "name": "pyth_token_id",
      "type": "TEXT",
      "nullable": true,
      "default": null,
      "primary_key": false
    },
    {
      "name": "cg_asset_name",
      "type": "TEXT",
      "nullable": true,
      "default": null,
      "primary_key": false
    },
    {
      "name": "score",
      "type": "REAL",
      "nullable": true,
      "default": null,
      "primary_key": false
    },
    {
      "name": "fetched_at",
      "type": "TEXT",
      "nullable": true,
      "default": null,
      "primary_key": false
    }
  ],
  "column_analysis": {
    "id": {
      "type": "TEXT",
      "nullable": true,
      "primary_key": true,
      "default": null,
      "total_rows": 615,
      "non_null": 615,
      "null_count": 0,
      "null_percentage": 0.0,
      "unique_values": 615,
      "uniqueness_ratio": 100.0,
      "min_length": 1,
      "max_length": 5,
      "avg_length": 4.91,
      "sample_values": [
        "1",
        "10000",
        "10001",
        "10002",
        "10003"
      ]
    },
    "ticker": {
      "type": "TEXT",
      "nullable": true,
      "primary_key": false,
      "default": null,
      "total_rows": 615,
      "non_null": 615,
      "null_count": 0,
      "null_percentage": 0.0,
      "unique_values": 615,
      "uniqueness_ratio": 100.0,
      "min_length": 3,
      "max_length": 59,
      "avg_length": 18.84,
      "sample_values": [
        "fomc",
        "bitcoin-hit-price-monthly",
        "largest-company",
        "xi-jinping-out",
        "ethereum-hit-price-monthly"
      ]
    },
    "slug": {
      "type": "TEXT",
      "nullable": true,
      "primary_key": false,
      "default": null,
      "total_rows": 615,
      "non_null": 615,
      "null_count": 0,
      "null_percentage": 0.0,
      "unique_values": 615,
      "uniqueness_ratio": 100.0,
      "min_length": 3,
      "max_length": 59,
      "avg_length": 18.84,
      "sample_values": [
        "1-free-app",
        "1-paid-app",
        "10-year-treasur",
        "123hottest-month-on-record",
        "2025-fide-world-cup"
      ]
    },
    "title": {
      "type": "TEXT",
      "nullable": true,
      "primary_key": false,
      "default": null,
      "total_rows": 615,
      "non_null": 615,
      "null_count": 0,
      "null_percentage": 0.0,
      "unique_values": 615,
      "uniqueness_ratio": 100.0,
      "min_length": 3,
      "max_length": 60,
      "avg_length": 19.27,
      "sample_values": [
        "FOMC",
        "Bitcoin Hit Price Monthly",
        "Largest Company",
        "Xi Jinping out",
        "Ethereum Hit Price Monthly"
      ]
    },
    "subtitle": {
      "type": "TEXT",
      "nullable": true,
      "primary_key": false,
      "default": null,
      "total_rows": 615,
      "non_null": 2,
      "null_count": 613,
      "null_percentage": 99.67,
      "unique_values": 2,
      "uniqueness_ratio": 100.0,
      "min_length": 3,
      "max_length": 3,
      "avg_length": 3.0,
      "sample_values": [
        "BTC",
        "ETH"
      ]
    },
    "series_type": {
      "type": "TEXT",
      "nullable": true,
      "primary_key": false,
      "default": null,
      "total_rows": 615,
      "non_null": 614,
      "null_count": 1,
      "null_percentage": 0.16,
      "unique_values": 1,
      "uniqueness_ratio": 0.16,
      "min_length": 6,
      "max_length": 6,
      "avg_length": 6.0,
      "sample_values": [
        "single"
      ],
      "top_values": [
        {
          "value": "single",
          "count": 614
        }
      ]
    },
    "recurrence": {
      "type": "TEXT",
      "nullable": true,
      "primary_key": false,
      "default": null,
      "total_rows": 615,
      "non_null": 614,
      "null_count": 1,
      "null_percentage": 0.16,
      "unique_values": 7,
      "uniqueness_ratio": 1.14,
      "min_length": 0,
      "max_length": 7,
      "avg_length": 5.72,
      "sample_values": [
        "monthly",
        "",
        "annual",
        "daily",
        "weekly"
      ],
      "top_values": [
        {
          "value": "daily",
          "count": 256
        },
        {
          "value": "monthly",
          "count": 147
        },
        {
          "value": "annual",
          "count": 103
        },
        {
          "value": "weekly",
          "count": 92
        },
        {
          "value": "",
          "count": 8
        }
      ]
    },
    "description": {
      "type": "TEXT",
      "nullable": true,
      "primary_key": false,
      "default": null,
      "total_rows": 615,
      "non_null": 1,
      "null_count": 614,
      "null_percentage": 99.84,
      "unique_values": 1,
      "uniqueness_ratio": 100.0,
      "min_length": 3,
      "max_length": 3,
      "avg_length": 3.0,
      "sample_values": [
        "NFL"
      ]
    },
    "image": {
      "type": "TEXT",
      "nullable": true,
      "primary_key": false,
      "default": null,
      "total_rows": 615,
      "non_null": 594,
      "null_count": 21,
      "null_percentage": 3.41,
      "unique_values": 96,
      "uniqueness_ratio": 16.16,
      "min_length": 0,
      "max_length": 264,
      "avg_length": 24.34,
      "sample_values": [
        "https://polymarket-upload.s3.us-east-2.amazonaws.com/jerome+powel+stern.png",
        "https://polymarket-upload.s3.us-east-2.amazonaws.com/bitcoin+colors.jpeg",
        "https://polymarket-upload.s3.us-east-2.amazonaws.com/largest-company-eoy-KS99l6lbxfCc.jpg",
        "",
        "https://polymarket-upload.s3.us-east-2.amazonaws.com/ethereum+colors.jpeg"
      ],
      "top_values": [
        {
          "value": "",
          "count": 442
        },
        {
          "value": "https://polymarket-upload.s3.us-east-2.amazonaws.c...",
          "count": 12
        },
        {
          "value": "https://polymarket-upload.s3.us-east-2.amazonaws.c...",
          "count": 9
        },
        {
          "value": "https://polymarket-upload.s3.us-east-2.amazonaws.c...",
          "count": 6
        },
        {
          "value": "https://polymarket-upload.s3.us-east-2.amazonaws.c...",
          "count": 6
        }
      ]
    },
    "icon": {
      "type": "TEXT",
      "nullable": true,
      "primary_key": false,
      "default": null,
      "total_rows": 615,
      "non_null": 594,
      "null_count": 21,
      "null_percentage": 3.41,
      "unique_values": 91,
      "uniqueness_ratio": 15.32,
      "min_length": 0,
      "max_length": 264,
      "avg_length": 24.3,
      "sample_values": [
        "https://polymarket-upload.s3.us-east-2.amazonaws.com/jerome+powel+stern.png",
        "https://polymarket-upload.s3.us-east-2.amazonaws.com/bitcoin+colors.jpeg",
        "https://polymarket-upload.s3.us-east-2.amazonaws.com/largest-company-eoy-KS99l6lbxfCc.jpg",
        "",
        "https://polymarket-upload.s3.us-east-2.amazonaws.com/ethereum+colors.jpeg"
      ],
      "top_values": [
        {
          "value": "",
          "count": 444
        },
        {
          "value": "https://polymarket-upload.s3.us-east-2.amazonaws.c...",
          "count": 16
        },
        {
          "value": "https://polymarket-upload.s3.us-east-2.amazonaws.c...",
          "count": 12
        },
        {
          "value": "https://polymarket-upload.s3.us-east-2.amazonaws.c...",
          "count": 9
        },
        {
          "value": "https://polymarket-upload.s3.us-east-2.amazonaws.c...",
          "count": 5
        }
      ]
    },
    "layout": {
      "type": "TEXT",
      "nullable": true,
      "primary_key": false,
      "default": null,
      "total_rows": 615,
      "non_null": 19,
      "null_count": 596,
      "null_percentage": 96.91,
      "unique_values": 1,
      "uniqueness_ratio": 5.26,
      "min_length": 7,
      "max_length": 7,
      "avg_length": 7.0,
      "sample_values": [
        "default"
      ],
      "top_values": [
        {
          "value": "default",
          "count": 19
        }
      ]
    },
    "active": {
      "type": "INTEGER",
      "nullable": true,
      "primary_key": false,
      "default": "1",
      "total_rows": 615,
      "non_null": 615,
      "null_count": 0,
      "null_percentage": 0.0,
      "min": 1,
      "max": 1,
      "avg": 1.0,
      "sum": 615,
      "median": 1,
      "distinct_values": 1,
      "value_distribution": [
        {
          "value": 1,
          "count": 615
        }
      ]
    },
    "closed": {
      "type": "INTEGER",
      "nullable": true,
      "primary_key": false,
      "default": "0",
      "total_rows": 615,
      "non_null": 615,
      "null_count": 0,
      "null_percentage": 0.0,
      "min": 0,
      "max": 0,
      "avg": 0,
      "sum": 0,
      "median": 0,
      "distinct_values": 1,
      "value_distribution": [
        {
          "value": 0,
          "count": 615
        }
      ]
    },
    "archived": {
      "type": "INTEGER",
      "nullable": true,
      "primary_key": false,
      "default": "0",
      "total_rows": 615,
      "non_null": 615,
      "null_count": 0,
      "null_percentage": 0.0,
      "min": 0,
      "max": 0,
      "avg": 0,
      "sum": 0,
      "median": 0,
      "distinct_values": 1,
      "value_distribution": [
        {
          "value": 0,
          "count": 615
        }
      ]
    },
    "new": {
      "type": "INTEGER",
      "nullable": true,
      "primary_key": false,
      "default": "0",
      "total_rows": 615,
      "non_null": 615,
      "null_count": 0,
      "null_percentage": 0.0,
      "min": 0,
      "max": 0,
      "avg": 0,
      "sum": 0,
      "median": 0,
      "distinct_values": 1,
      "value_distribution": [
        {
          "value": 0,
          "count": 615
        }
      ]
    },
    "featured": {
      "type": "INTEGER",
      "nullable": true,
      "primary_key": false,
      "default": "0",
      "total_rows": 615,
      "non_null": 615,
      "null_count": 0,
      "null_percentage": 0.0,
      "min": 0,
      "max": 1,
      "avg": 0.01,
      "sum": 9,
      "median": 0,
      "distinct_values": 2,
      "value_distribution": [
        {
          "value": 0,
          "count": 606
        },
        {
          "value": 1,
          "count": 9
        }
      ]
    },
    "restricted": {
      "type": "INTEGER",
      "nullable": true,
      "primary_key": false,
      "default": "0",
      "total_rows": 615,
      "non_null": 615,
      "null_count": 0,
      "null_percentage": 0.0,
      "min": 0,
      "max": 1,
      "avg": 0.98,
      "sum": 602,
      "median": 1,
      "distinct_values": 2,
      "value_distribution": [
        {
          "value": 1,
          "count": 602
        },
        {
          "value": 0,
          "count": 13
        }
      ]
    },
    "is_template": {
      "type": "INTEGER",
      "nullable": true,
      "primary_key": false,
      "default": "0",
      "total_rows": 615,
      "non_null": 615,
      "null_count": 0,
      "null_percentage": 0.0,
      "min": 0,
      "max": 0,
      "avg": 0,
      "sum": 0,
      "median": 0,
      "distinct_values": 1,
      "value_distribution": [
        {
          "value": 0,
          "count": 615
        }
      ]
    },
    "template_variables": {
      "type": "INTEGER",
      "nullable": true,
      "primary_key": false,
      "default": "0",
      "total_rows": 615,
      "non_null": 615,
      "null_count": 0,
      "null_percentage": 0.0,
      "min": 0,
      "max": 0,
      "avg": 0,
      "sum": 0,
      "median": 0,
      "distinct_values": 1,
      "value_distribution": [
        {
          "value": 0,
          "count": 615
        }
      ]
    },
    "published_at": {
      "type": "TEXT",
      "nullable": true,
      "primary_key": false,
      "default": null,
      "total_rows": 615,
      "non_null": 18,
      "null_count": 597,
      "null_percentage": 97.07,
      "earliest": "2022-10-13 00:34:49.115+00",
      "latest": "2024-06-14 18:57:17.756574+00",
      "distinct_values": 18
    },
    "created_by": {
      "type": "TEXT",
      "nullable": true,
      "primary_key": false,
      "default": null,
      "total_rows": 615,
      "non_null": 17,
      "null_count": 598,
      "null_percentage": 97.24,
      "earliest": "15",
      "latest": "9",
      "distinct_values": 2
    },
    "updated_by": {
      "type": "TEXT",
      "nullable": true,
      "primary_key": false,
      "default": null,
      "total_rows": 615,
      "non_null": 17,
      "null_count": 598,
      "null_percentage": 97.24,
      "earliest": "15",
      "latest": "9",
      "distinct_values": 3
    },
    "created_at": {
      "type": "TEXT",
      "nullable": true,
      "primary_key": false,
      "default": null,
      "total_rows": 615,
      "non_null": 615,
      "null_count": 0,
      "null_percentage": 0.0,
      "earliest": "2022-10-13T00:34:06.557Z",
      "latest": "2025-11-21T21:46:44.298711Z",
      "distinct_values": 605
    },
    "updated_at": {
      "type": "TEXT",
      "nullable": true,
      "primary_key": false,
      "default": null,
      "total_rows": 615,
      "non_null": 615,
      "null_count": 0,
      "null_percentage": 0.0,
      "earliest": "2025-11-22T21:16:42.841013Z",
      "latest": "2025-11-22T22:42:43.383593Z",
      "distinct_values": 615
    },
    "comments_enabled": {
      "type": "INTEGER",
      "nullable": true,
      "primary_key": false,
      "default": "0",
      "total_rows": 615,
      "non_null": 615,
      "null_count": 0,
      "null_percentage": 0.0,
      "min": 0,
      "max": 0,
      "avg": 0,
      "sum": 0,
      "median": 0,
      "distinct_values": 1,
      "value_distribution": [
        {
          "value": 0,
          "count": 615
        }
      ]
    },
    "competitive": {
      "type": "TEXT",
      "nullable": true,
      "primary_key": false,
      "default": null,
      "total_rows": 615,
      "non_null": 18,
      "null_count": 597,
      "null_percentage": 97.07,
      "unique_values": 1,
      "uniqueness_ratio": 5.56,
      "min_length": 1,
      "max_length": 1,
      "avg_length": 1.0,
      "sample_values": [
        "0"
      ],
      "top_values": [
        {
          "value": "0",
          "count": 18
        }
      ]
    },
    "volume_24hr": {
      "type": "REAL",
      "nullable": true,
      "primary_key": false,
      "default": "0",
      "total_rows": 615,
      "non_null": 18,
      "null_count": 597,
      "null_percentage": 97.07,
      "min": 0.0,
      "max": 0.0,
      "avg": 0,
      "sum": 0.0,
      "median": 0.0,
      "distinct_values": 1,
      "value_distribution": [
        {
          "value": 0.0,
          "count": 18
        }
      ]
    },
    "volume": {
      "type": "REAL",
      "nullable": true,
      "primary_key": false,
      "default": "0",
      "total_rows": 615,
      "non_null": 343,
      "null_count": 272,
      "null_percentage": 44.23,
      "min": 1.0204,
      "max": 145922392.663339,
      "avg": 2226709.67,
      "sum": 763761417.704291,
      "median": 131325.413268,
      "distinct_values": 333
    },
    "liquidity": {
      "type": "REAL",
      "nullable": true,
      "primary_key": false,
      "default": "0",
      "total_rows": 615,
      "non_null": 353,
      "null_count": 262,
      "null_percentage": 42.6,
      "min": 4.75,
      "max": 14461330.65655,
      "avg": 449700.68,
      "sum": 158744338.8224,
      "median": 23598.62211,
      "distinct_values": 352
    },
    "start_date": {
      "type": "TEXT",
      "nullable": true,
      "primary_key": false,
      "default": null,
      "total_rows": 615,
      "non_null": 13,
      "null_count": 602,
      "null_percentage": 97.89,
      "earliest": "2021-01-01T17:00:00Z",
      "latest": "2024-06-14T18:57:17.756574Z",
      "distinct_values": 6
    },
    "pyth_token_id": {
      "type": "TEXT",
      "nullable": true,
      "primary_key": false,
      "default": null,
      "total_rows": 615,
      "non_null": 2,
      "null_count": 613,
      "null_percentage": 99.67,
      "unique_values": 2,
      "uniqueness_ratio": 100.0,
      "min_length": 66,
      "max_length": 66,
      "avg_length": 66.0,
      "sample_values": [
        "0xe62df6c8b4a85fe1a67db44dc12de5db330f7ac66b72dc658afedf0f4a415b43",
        "0xff61491a931112ddf1bd8147cd1b641375f79f5825126d665480874634fd0ace"
      ]
    },
    "cg_asset_name": {
      "type": "TEXT",
      "nullable": true,
      "primary_key": false,
      "default": null,
      "total_rows": 615,
      "non_null": 2,
      "null_count": 613,
      "null_percentage": 99.67,
      "unique_values": 2,
      "uniqueness_ratio": 100.0,
      "min_length": 7,
      "max_length": 8,
      "avg_length": 7.5,
      "sample_values": [
        "bitcoin",
        "ethereum"
      ]
    },
    "score": {
      "type": "REAL",
      "nullable": true,
      "primary_key": false,
      "default": null,
      "total_rows": 615,
      "non_null": 0,
      "null_count": 615,
      "null_percentage": 100.0
    },
    "fetched_at": {
      "type": "TEXT",
      "nullable": true,
      "primary_key": false,
      "default": null,
      "total_rows": 615,
      "non_null": 615,
      "null_count": 0,
      "null_percentage": 0.0,
      "earliest": "2025-11-22T16:53:21.402338",
      "latest": "2025-11-22T16:53:21.444921",
      "distinct_values": 615
    }
  },
  "sample_rows": [
    "id:35 | ticker:fomc | slug:fomc | title:FOMC | subtitle:NULL | series_type:single | recurrence:monthly | description:NULL | image:https://polymarket-upload.s3.u... | icon:https://polymarket-upload.s3.u... | ...",
    "id:10016 | ticker:bitcoin-hit-price-monthly | slug:bitcoin-hit-price-monthly | title:Bitcoin Hit Price Monthly | subtitle:NULL | series_type:single | recurrence:monthly | description:NULL | image:https://polymarket-upload.s3.u... | icon:https://polymarket-upload.s3.u... | ...",
    "id:10029 | ticker:largest-company | slug:largest-company | title:Largest Company | subtitle:NULL | series_type:single | recurrence:monthly | description:NULL | image:https://polymarket-upload.s3.u... | icon:https://polymarket-upload.s3.u... | ...",
    "id:10150 | ticker:xi-jinping-out | slug:xi-jinping-out | title:Xi Jinping out | subtitle:NULL | series_type:single | recurrence:monthly | description:NULL | image: | icon: | ...",
    "id:10017 | ticker:ethereum-hit-price-monthly | slug:ethereum-hit-price-monthly | title:Ethereum Hit Price Monthly | subtitle:NULL | series_type:single | recurrence:monthly | description:NULL | image:https://polymarket-upload.s3.u... | icon:https://polymarket-upload.s3.u... | ..."
  ],
  "indexes": [
    {
      "name": "idx_series_slug",
      "unique": false
    },
    {
      "name": "idx_series_volume",
      "unique": false
    },
    {
      "name": "sqlite_autoindex_series_2",
      "unique": true
    },
    {
      "name": "sqlite_autoindex_series_1",
      "unique": true
    }
  ],
  "relationships": {
    "foreign_keys": [],
    "referenced_by": [
      {
        "table": "event_series",
        "column": "series_id"
      },
      {
        "table": "series_tags",
        "column": "series_id"
      },
      {
        "table": "series_categories",
        "column": "series_id"
      },
      {
        "table": "series_collections",
        "column": "series_id"
      },
      {
        "table": "series_chats",
        "column": "series_id"
      },
      {
        "table": "series_events",
        "column": "series_id"
      }
    ]
  }
}